<mods xmlns="http://www.loc.gov/mods/v3" xmlns:xsi="http://www.w3.org/2001/XMLSchema-instance" xmlns:xlink="http://www.w3.org/1999/xlink" version="3.6" xsi:schemaLocation="http://www.loc.gov/mods/v3 http://cluster-schemas.uni-hd.de/modsCluster.xsd" ID="uuid-0A049D52-86E1-47E1-9BC2-527E86589169"><name type="personal" xlink:href=""><namePart lang="chi" script="Hant">本居宣長著</namePart><role><roleTerm type="text">author</roleTerm></role></name><titleInfo lang="chi" script="Hant"><title>古今集遠鏡</title></titleInfo><note type="from">日本書目志,卷十一,文學門,歌集,p 983</note><note type="price">一圓二角</note><identifier type="mh">book_5381</identifier></mods>