<mods xmlns="http://www.loc.gov/mods/v3" xmlns:xsi="http://www.w3.org/2001/XMLSchema-instance" xmlns:xlink="http://www.w3.org/1999/xlink" version="3.6" xsi:schemaLocation="http://www.loc.gov/mods/v3 http://cluster-schemas.uni-hd.de/modsCluster.xsd" ID="uuid-0B858CFD-9A6C-471E-8A55-84AB8C5F165A"><name type="personal" xlink:href=""><namePart lang="chi" script="Hant">一勇齋國芳畫　池田義信輯錄</namePart><role><roleTerm type="text">author</roleTerm></role></name><titleInfo lang="chi" script="Hant"><title>忠臣銘銘畫傳</title></titleInfo><note type="from">日本書目志,卷十三,美術門,繪畫書,p 1100</note><note type="price">三角</note><identifier type="mh">book_7010</identifier></mods>